{
  "$schema": "https://raw.githubusercontent.com/electron-userland/electron-builder/master/packages/app-builder-lib/scheme.json",
  "appId": "com.sanctuary.app",
  "productName": "Sanctuary",
  "copyright": "Copyright © 2024 Sanctuary Team",
  "directories": {
    "output": "release",
    "buildResources": "build"
  },
  "files": [
    "dist/**/*",
    "package.json"
  ],
  "extraResources": [
    {
      "from": "build/icon-light.png",
      "to": "icon-light.png"
    },
    {
      "from": "build/icon-dark.png",
      "to": "icon-dark.png"
    }
  ],
  "asar": true,
  "asarUnpack": [
    "**/*.node"
  ],
  "mac": {
    "category": "public.app-category.productivity",
    "target": [
      {
        "target": "dmg",
        "arch": ["x64", "arm64"]
      }
    ],
    "icon": "build/icon.icns",
    "darkModeSupport": true,
    "hardenedRuntime": true,
    "gatekeeperAssess": false,
    "entitlements": "build/entitlements.mac.plist",
    "entitlementsInherit": "build/entitlements.mac.plist",
    "notarize": false
  },
  "dmg": {
    "contents": [
      {
        "x": 130,
        "y": 220
      },
      {
        "x": 410,
        "y": 220,
        "type": "link",
        "path": "/Applications"
      }
    ],
    "window": {
      "width": 540,
      "height": 380
    }
  },
  "win": {
    "target": [
      {
        "target": "nsis",
        "arch": ["x64"]
      }
    ],
    "icon": "build/icon.ico",
    "artifactName": "${productName}-${version}-${arch}.${ext}"
  },
  "nsis": {
    "oneClick": false,
    "perMachine": false,
    "allowToChangeInstallationDirectory": true,
    "deleteAppDataOnUninstall": false,
    "createDesktopShortcut": true,
    "createStartMenuShortcut": true,
    "shortcutName": "Sanctuary"
  },
  "linux": {
    "target": [
      {
        "target": "AppImage",
        "arch": ["x64"]
      }
    ],
    "category": "Office",
    "icon": "build/icons"
  },
  "publish": {
    "provider": "github",
    "owner": "sanctuary",
    "repo": "sanctuary"
  }
}
